traits/__init__.py
traits/base.py
traits/py.typed
django_traits-0.0.1.dist-info/LICENSE
django_traits-0.0.1.dist-info/METADATA
django_traits-0.0.1.dist-info/WHEEL
django_traits-0.0.1.dist-info/top_level.txt
django_traits-0.0.1.dist-info/RECORD
