Metadata-Version: 2.1
Name: django-traits
Version: 0.0.1
Summary: Traits for Django
Home-page: https://github.com/5monkeys/django-traits/
Author: Anton Agestam
Author-email: git@antonagestam.se
License: BSD-3-Clause License
Platform: UNKNOWN
Classifier: Intended Audience :: Developers
Classifier: Operating System :: OS Independent
Classifier: Programming Language :: Python
Classifier: Programming Language :: Python :: 3
Classifier: Programming Language :: Python :: 3 :: Only
Classifier: Programming Language :: Python :: 3.9
Classifier: Programming Language :: Python :: 3.10
Classifier: Development Status :: 4 - Beta
Requires-Python: >=3.9
License-File: LICENSE
Requires-Dist: Django (>=3.2)
Provides-Extra: test
Requires-Dist: pytest ; extra == 'test'
Requires-Dist: pytest-django ; extra == 'test'
Requires-Dist: pytest-mypy-plugins ; extra == 'test'
Requires-Dist: django-stubs ; extra == 'test'
Requires-Dist: coverage ; extra == 'test'
